setup.py
YoutubetoMp3/__init__.py
YoutubetoMp3/main.py
YoutubetoMp3.egg-info/PKG-INFO
YoutubetoMp3.egg-info/SOURCES.txt
YoutubetoMp3.egg-info/dependency_links.txt
YoutubetoMp3.egg-info/entry_points.txt
YoutubetoMp3.egg-info/top_level.txt